typedjinja/__init__.py
typedjinja/__main__.py
typedjinja/jedi_complete.py
typedjinja/lsp_server.py
typedjinja/parser.py
typedjinja/schema.py
typedjinja-0.1.3.dist-info/licenses/LICENSE
typedjinja-0.1.3.dist-info/METADATA
typedjinja-0.1.3.dist-info/WHEEL
typedjinja-0.1.3.dist-info/top_level.txt
typedjinja-0.1.3.dist-info/RECORD
