Metadata-Version: 2.4
Name: typedjinja
Version: 0.1.3
Summary: Type safety and editor intelligence for Jinja2 templates.
Author-email: Daniel Rodriguez Mariblanca <dakixr@gmail.com>
License: MIT
Project-URL: Homepage, https://github.com/dakixr/TypedJinja
Project-URL: Repository, https://github.com/dakixr/TypedJinja.git
Classifier: Programming Language :: Python :: 3
Classifier: Programming Language :: Python :: 3.12
Classifier: License :: OSI Approved :: MIT License
Classifier: Operating System :: OS Independent
Classifier: Intended Audience :: Developers
Classifier: Topic :: Software Development :: Libraries :: Python Modules
Classifier: Topic :: Text Processing :: Markup :: HTML
Requires-Python: >=3.12
License-File: LICENSE
Requires-Dist: jinja2>=3.1.0
Requires-Dist: jedi>=0.19.2
Requires-Dist: tree-sitter>=0.24.0
Requires-Dist: tree-sitter-jinja>=0.3.3
Provides-Extra: dev
Requires-Dist: pytest>=7.0; extra == "dev"
Requires-Dist: ruff>=0.1.0; extra == "dev"
Dynamic: license-file
